{"nodes": [{"id": "d_users_zakio_desktop_lango_english_center_project_fully_lango_app_src_app_admin_lms_builder_page_tsx", "label": "page.tsx", "file_type": "code", "source_file": "D:\\Users\\zakio\\Desktop\\Lango english center project fully\\lango-app\\src\\app\\(admin)\\lms\\builder\\page.tsx", "source_location": "L1"}, {"id": "builder_page_lessontype", "label": "LessonType", "file_type": "code", "source_file": "D:\\Users\\zakio\\Desktop\\Lango english center project fully\\lango-app\\src\\app\\(admin)\\lms\\builder\\page.tsx", "source_location": "L8"}, {"id": "builder_page_lesson", "label": "Lesson", "file_type": "code", "source_file": "D:\\Users\\zakio\\Desktop\\Lango english center project fully\\lango-app\\src\\app\\(admin)\\lms\\builder\\page.tsx", "source_location": "L10"}, {"id": "builder_page_module", "label": "Module", "file_type": "code", "source_file": "D:\\Users\\zakio\\Desktop\\Lango english center project fully\\lango-app\\src\\app\\(admin)\\lms\\builder\\page.tsx", "source_location": "L11"}, {"id": "builder_page_lessonicons", "label": "lessonIcons", "file_type": "code", "source_file": "D:\\Users\\zakio\\Desktop\\Lango english center project fully\\lango-app\\src\\app\\(admin)\\lms\\builder\\page.tsx", "source_location": "L13"}, {"id": "builder_page_lessoncolors", "label": "lessonColors", "file_type": "code", "source_file": "D:\\Users\\zakio\\Desktop\\Lango english center project fully\\lango-app\\src\\app\\(admin)\\lms\\builder\\page.tsx", "source_location": "L14"}, {"id": "builder_page_initialmodules", "label": "initialModules", "file_type": "code", "source_file": "D:\\Users\\zakio\\Desktop\\Lango english center project fully\\lango-app\\src\\app\\(admin)\\lms\\builder\\page.tsx", "source_location": "L20"}, {"id": "builder_page_lmsbuilderpage", "label": "LMSBuilderPage()", "file_type": "code", "source_file": "D:\\Users\\zakio\\Desktop\\Lango english center project fully\\lango-app\\src\\app\\(admin)\\lms\\builder\\page.tsx", "source_location": "L40"}], "edges": [{"source": "d_users_zakio_desktop_lango_english_center_project_fully_lango_app_src_app_admin_lms_builder_page_tsx", "target": "react", "relation": "imports_from", "context": "import", "confidence": "EXTRACTED", "source_file": "D:\\Users\\zakio\\Desktop\\Lango english center project fully\\lango-app\\src\\app\\(admin)\\lms\\builder\\page.tsx", "source_location": "L3", "weight": 1.0}, {"source": "d_users_zakio_desktop_lango_english_center_project_fully_lango_app_src_app_admin_lms_builder_page_tsx", "target": "lucide_react", "relation": "imports_from", "context": "import", "confidence": "EXTRACTED", "source_file": "D:\\Users\\zakio\\Desktop\\Lango english center project fully\\lango-app\\src\\app\\(admin)\\lms\\builder\\page.tsx", "source_location": "L4", "weight": 1.0}, {"source": "d_users_zakio_desktop_lango_english_center_project_fully_lango_app_src_app_admin_lms_builder_page_tsx", "target": "d_users_zakio_desktop_lango_english_center_project_fully_lango_app_src_components_ui_button_tsx", "relation": "imports_from", "context": "import", "confidence": "EXTRACTED", "source_file": "D:\\Users\\zakio\\Desktop\\Lango english center project fully\\lango-app\\src\\app\\(admin)\\lms\\builder\\page.tsx", "source_location": "L5", "weight": 1.0}, {"source": "d_users_zakio_desktop_lango_english_center_project_fully_lango_app_src_app_admin_lms_builder_page_tsx", "target": "ui_button_button", "relation": "imports", "context": "import", "confidence": "EXTRACTED", "source_file": "D:\\Users\\zakio\\Desktop\\Lango english center project fully\\lango-app\\src\\app\\(admin)\\lms\\builder\\page.tsx", "source_location": "L5", "weight": 1.0}, {"source": "d_users_zakio_desktop_lango_english_center_project_fully_lango_app_src_app_admin_lms_builder_page_tsx", "target": "d_users_zakio_desktop_lango_english_center_project_fully_lango_app_src_components_ui_input_tsx", "relation": "imports_from", "context": "import", "confidence": "EXTRACTED", "source_file": "D:\\Users\\zakio\\Desktop\\Lango english center project fully\\lango-app\\src\\app\\(admin)\\lms\\builder\\page.tsx", "source_location": "L6", "weight": 1.0}, {"source": "d_users_zakio_desktop_lango_english_center_project_fully_lango_app_src_app_admin_lms_builder_page_tsx", "target": "ui_input_input", "relation": "imports", "context": "import", "confidence": "EXTRACTED", "source_file": "D:\\Users\\zakio\\Desktop\\Lango english center project fully\\lango-app\\src\\app\\(admin)\\lms\\builder\\page.tsx", "source_location": "L6", "weight": 1.0}, {"source": "d_users_zakio_desktop_lango_english_center_project_fully_lango_app_src_app_admin_lms_builder_page_tsx", "target": "builder_page_lessontype", "relation": "contains", "confidence": "EXTRACTED", "source_file": "D:\\Users\\zakio\\Desktop\\Lango english center project fully\\lango-app\\src\\app\\(admin)\\lms\\builder\\page.tsx", "source_location": "L8", "weight": 1.0}, {"source": "d_users_zakio_desktop_lango_english_center_project_fully_lango_app_src_app_admin_lms_builder_page_tsx", "target": "builder_page_lesson", "relation": "contains", "confidence": "EXTRACTED", "source_file": "D:\\Users\\zakio\\Desktop\\Lango english center project fully\\lango-app\\src\\app\\(admin)\\lms\\builder\\page.tsx", "source_location": "L10", "weight": 1.0}, {"source": "d_users_zakio_desktop_lango_english_center_project_fully_lango_app_src_app_admin_lms_builder_page_tsx", "target": "builder_page_module", "relation": "contains", "confidence": "EXTRACTED", "source_file": "D:\\Users\\zakio\\Desktop\\Lango english center project fully\\lango-app\\src\\app\\(admin)\\lms\\builder\\page.tsx", "source_location": "L11", "weight": 1.0}, {"source": "d_users_zakio_desktop_lango_english_center_project_fully_lango_app_src_app_admin_lms_builder_page_tsx", "target": "builder_page_lessonicons", "relation": "contains", "confidence": "EXTRACTED", "source_file": "D:\\Users\\zakio\\Desktop\\Lango english center project fully\\lango-app\\src\\app\\(admin)\\lms\\builder\\page.tsx", "source_location": "L13", "weight": 1.0}, {"source": "d_users_zakio_desktop_lango_english_center_project_fully_lango_app_src_app_admin_lms_builder_page_tsx", "target": "builder_page_lessoncolors", "relation": "contains", "confidence": "EXTRACTED", "source_file": "D:\\Users\\zakio\\Desktop\\Lango english center project fully\\lango-app\\src\\app\\(admin)\\lms\\builder\\page.tsx", "source_location": "L14", "weight": 1.0}, {"source": "d_users_zakio_desktop_lango_english_center_project_fully_lango_app_src_app_admin_lms_builder_page_tsx", "target": "builder_page_initialmodules", "relation": "contains", "confidence": "EXTRACTED", "source_file": "D:\\Users\\zakio\\Desktop\\Lango english center project fully\\lango-app\\src\\app\\(admin)\\lms\\builder\\page.tsx", "source_location": "L20", "weight": 1.0}, {"source": "d_users_zakio_desktop_lango_english_center_project_fully_lango_app_src_app_admin_lms_builder_page_tsx", "target": "builder_page_lmsbuilderpage", "relation": "contains", "confidence": "EXTRACTED", "source_file": "D:\\Users\\zakio\\Desktop\\Lango english center project fully\\lango-app\\src\\app\\(admin)\\lms\\builder\\page.tsx", "source_location": "L40", "weight": 1.0}], "raw_calls": [{"caller_nid": "builder_page_lmsbuilderpage", "callee": "useState", "is_member_call": false, "source_file": "D:\\Users\\zakio\\Desktop\\Lango english center project fully\\lango-app\\src\\app\\(admin)\\lms\\builder\\page.tsx", "source_location": "L41"}, {"caller_nid": "builder_page_lmsbuilderpage", "callee": "useState", "is_member_call": false, "source_file": "D:\\Users\\zakio\\Desktop\\Lango english center project fully\\lango-app\\src\\app\\(admin)\\lms\\builder\\page.tsx", "source_location": "L42"}, {"caller_nid": "builder_page_lmsbuilderpage", "callee": "reduce", "is_member_call": true, "source_file": "D:\\Users\\zakio\\Desktop\\Lango english center project fully\\lango-app\\src\\app\\(admin)\\lms\\builder\\page.tsx", "source_location": "L68"}, {"caller_nid": "builder_page_lmsbuilderpage", "callee": "map", "is_member_call": true, "source_file": "D:\\Users\\zakio\\Desktop\\Lango english center project fully\\lango-app\\src\\app\\(admin)\\lms\\builder\\page.tsx", "source_location": "L118"}]}